voc2yolo/__init__.py
voc2yolo/converter.py
voc2yolo/utils.py
voc2yolo-0.1.0.dist-info/METADATA
voc2yolo-0.1.0.dist-info/WHEEL
voc2yolo-0.1.0.dist-info/top_level.txt
voc2yolo-0.1.0.dist-info/RECORD
